{"ocr_results":[{"text":"勇往直前，不断革命","box":[[334,216],[785,234],[784,263],[333,245]]},{"text":"一学习党的基本路线的体会","box":[[403,280],[718,294],[717,317],[402,303]]},{"text":"我过去头脑里有许多怕字，怕天下大乱，怕情况复杂，怕打击","box":[[231,345],[938,361],[937,397],[230,381]]},{"text":"报复，基致（至）怕大机关大干部。通过紧张的学习，特别是势如","box":[[173,385],[944,396],[944,438],[172,427]]},{"text":"破付的批林批孔运动，使我感到这种畏畏缩缩的精神壮（状）态是","box":[[168,425],[949,437],[948,479],[168,467]]},{"text":"党性不纯的表现，它是与党的基本路线相对立的。事物发展的规律","box":[[163,468],[954,479],[953,521],[163,510]]},{"text":"总是：大乱之后方而新，世界总是在大风大浪的大变动中前进的。","box":[[159,512],[947,523],[947,562],[158,551]]},{"text":"党的基本路线所以是胜利线，就是因为它指引我们在大交动的暴风","box":[[153,558],[965,566],[965,605],[152,597]]},{"text":"聚雨中把握住复杂的时局，在曲折迁回的斗争中争取无产阶级的主","box":[[148,604],[971,614],[971,652],[147,642]]},{"text":"动权，加速无产阶级革命的进程。党的基本路线所以是照耀我们各","box":[[144,655],[973,664],[973,696],[144,687]]},{"text":"项工作前进的灯塔，就是因为它揭示旧制度是怎样必然的在无比痛","box":[[138,699],[980,708],[979,743],[138,734]]},{"text":"苦中走向灭亡，新制度是怎样必然的在无比限难中走向胜利的历史","box":[[131,751],[987,759],[986,792],[131,783]]},{"text":"总趋势，它的核心就是要革命，要批判，要破旧立新，要搞马克思","box":[[123,802],[991,810],[991,842],[122,834]]},{"text":"主义，要使现存的一切都完全革命化。","box":[[118,859],[616,860],[616,887],[118,886]]},{"text":"我感到在党的基本路线指引下所进行的各次社会大变动、大革","box":[[171,910],[1003,919],[1003,948],[171,939]]},{"text":"命，都如同把古老的中国推进了一座大熔炉，每变动一次都产生出","box":[[101,966],[1008,976],[1007,1004],[101,995]]},{"text":"社会主义的新因素，排泄出旧社会的陈渣腐沫。每变动一次，都使","box":[[93,1025],[1015,1033],[1015,1062],[92,1054]]},{"text":"更多的人志愿向新制度靠拢，同旧制度决裂。","box":[[88,1085],[718,1089],[718,1118],[88,1114]]},{"text":"大乱大变动就必然会遇到大阻力大斗争。比如我国的一化三改","box":[[147,1143],[1023,1152],[1023,1184],[146,1175]]},{"text":"是一次惊天动地的大变动，这是我国破天荒向传统的所有制所进行","box":[[77,1204],[1027,1212],[1027,1245],[77,1237]]},{"text":"的大进军，那一次的阻力是大的，骂街的人是凶的，但是那一次我","box":[[74,1268],[1033,1274],[1033,1307],[74,1300]]},{"text":"11","box":[[890,1351],[987,1351],[987,1379],[890,1379]]}],"dimensions":{"height":1440,"width":1080}}