{"ocr_results":[{"text":"永球商场","box":[[119,78],[291,75],[291,103],[119,105]]},{"text":"米说，长江二十五个单位，轮船公司五个，也是按这样成绩前进的。所以，应该说大多数是","box":[[682,82],[1167,89],[1167,105],[682,98]]},{"text":"取得了很大成绩。因而，运输量、运输速度不新增长，在这方面你们比我更清楚，不需再重","box":[[681,100],[1168,107],[1168,123],[681,116]]},{"text":"总理、陈伯达、康生、江青","box":[[143,112],[443,112],[443,141],[143,141]]},{"text":"复了。但为什医达到这样的成绩，还离我句需要的指标还有原离？这一点，今天是我们在庆","box":[[682,119],[1168,125],[1168,141],[681,135]]},{"text":"贺你们取得伟大成绩当中，特别要和你们说一说。","box":[[684,138],[999,144],[999,157],[684,151]]},{"text":"姚文元等同志在接見全國铁路、交通","box":[[95,148],[488,152],[487,174],[95,169]]},{"text":"现在还有那磨儿个关键性的铁路运点，关键性的港口，要通不过的话，其他运输线路","box":[[685,157],[1168,163],[1168,177],[685,170]]},{"text":"也期不过，这就叫交通！交通的特点是近代化的组织，只要有一个站道不过，其他站最然","box":[[684,174],[1168,181],[1168,195],[684,189]]},{"text":"会藏全体代表时的重要需斋","box":[[141,185],[437,189],[436,211],[141,207]]},{"text":"开出了列车，还是通不过，这就是个关德还有卸货，运到一个地方卸不下来，把车辆占","box":[[684,193],[1167,200],[1167,214],[684,206]]},{"text":"着，服占了，那您势必货多卸不下来地识那里，或着是卸下了但又运不走，占满了仓库，这","box":[[683,211],[1168,217],[1168,231],[683,225]]},{"text":"（根据記录整理，未經首長审）","box":[[169,228],[409,232],[408,247],[168,243]]},{"text":"32E","box":[[52,240],[116,240],[116,252],[52,252]]},{"text":"也是不行的这一点，我相信你们比我还要着急，因为你们是愿意一个续路局一片红的。比","box":[[683,231],[1168,235],[1168,248],[683,244]]},{"text":"如，这两全月你们是争取了许多铁路局一片红了哪，一片红就是说局、分局、段、站，都成","box":[[682,247],[1171,251],[1170,267],[682,263]]},{"text":"立了车命委员会，这是一件不容易的事，从你们的简报上看，确实有这样的地方一片红。比","box":[[681,265],[1171,269],[1170,285],[681,281]]},{"text":"时间：一九六八年五月十二口晚九时至十一时二十分","box":[[42,276],[327,280],[327,293],[42,290]]},{"text":"中","box":[[340,275],[356,273],[357,282],[342,285]]},{"text":"如最新的唯天晚上收到的简报，全国十八全铁路局中，有哈尔滨、呼和浩待、兰州、齐齐哈","box":[[682,284],[1170,289],[1170,302],[682,298]]},{"text":"地点：人民大会堂","box":[[42,296],[226,297],[226,310],[41,309]]},{"text":"在","box":[[241,297],[355,300],[355,313],[241,310]]},{"text":"尔、州、北京、郑州、昆明等八个局实现了一片红，这是一件好事幕！实现了一片红的仅区是八","box":[[682,303],[1172,307],[1172,321],[682,317]]},{"text":"五月十二日，总理、陈伯达、康生、江青、姚文元等中央领导同志接见了全体代表，并","box":[[65,313],[537,321],[537,334],[65,327]]},{"text":"个铁路局，还有十个铁路局没有一片红，我们还要推动其他十个局。如头十八个铁路局来说，","box":[[681,321],[1170,325],[1170,338],[681,334]]},{"text":"作了重要指示。陪同参加接见的有李先念、谢富治、黄永胜、吴法宪、汪东兴、温玉成等同","box":[[39,331],[536,338],[536,352],[39,345]]},{"text":"有的革命委员会成立了，一片红了有的是大联合，但不是十八个关路局全如此。比如，就东","box":[[683,340],[1173,343],[1173,357],[683,354]]},{"text":"志。当总理、陈伯达、康生、江青、姚文元等中央领导同志进入大厅时，全体代表热烈高呼：","box":[[39,350],[530,357],[530,370],[39,363]]},{"text":"北来说，关键在沈阳。前天成立了辽宁省、沈阳市革命委员会，因而推动了沈阳路局也达","box":[[682,358],[1172,360],[1172,374],[682,372]]},{"text":"“毛主席万岁！毛主席万万岁！”“祝毛主席万寿无疆！万寿无疆！","box":[[42,369],[422,372],[422,386],[42,382]]},{"text":"成了成立革命三结合协议，你们回去就可能成立了。但吉林铁路局还没有实现，吉林省革命","box":[[682,376],[1173,379],[1173,393],[682,391]]},{"text":"江膏：同志们：同志们好！（众高呼：向江青同志学习！向江青同志致敬！毛主席万岁！","box":[[60,387],[531,393],[530,406],[60,400]]},{"text":"委员会成立在先，但没有推动好，需要你们回去推动。比如说，中南这方面郑州铁路局星然","box":[[682,395],[1175,398],[1175,411],[682,408]]},{"text":"毛主席万万岁！）现在我们开会，请总理给我们讲话，（众高呼：向总理学习！向总理致敬1）","box":[[35,406],[531,411],[531,424],[35,419]]},{"text":"片红了，可是最关键的郑州分局、郑州北站这个口子通不过，还是江岸车站不过，全线运","box":[[682,413],[1174,415],[1174,429],[682,427]]},{"text":"总理：向间志们致敬！向间志们学习！同志们！你们来北京，是根据中央文革在一次会","box":[[58,425],[535,430],[535,441],[58,436]]},{"text":"信就受影响。尽管是一片红的郑州铁路局，但还积压车辆。比如昨天郑州局这线上还是","box":[[681,431],[1176,434],[1176,448],[681,444]]},{"text":"该上的提议，经我们伟大领抽毛主席和他的亲密战友林付主席批准来开会的。（众高呼；","box":[[34,442],[528,447],[528,460],[33,456]]},{"text":"保压相当大的车，保留车达到三千多师。十一日全国保留车一万二千多朝，郑州一个点航","box":[[683,450],[1175,452],[1175,465],[683,463]]},{"text":"毛主席万岁！毛主席万万岁！）全国铁路、交通会议讨论了抓革命促业务。从三月五日开始到","box":[[34,460],[535,466],[534,481],[33,475]]},{"text":"占四分之一这就说明，尽管有的铁路局实现了一片红，一个车站工作做不好，也会影响全","box":[[682,468],[1177,471],[1177,485],[682,481]]},{"text":"现在已经两个多月了。在这中间，全体代表参加了“五一”国际劳动节观礼，特别是五月八","box":[[32,480],[535,484],[535,497],[32,493]]},{"text":"线路。郑州高的同志们想一想，一个点不通，民它点很着急，武汉分局再其分局也很着","box":[[683,487],[1177,490],[1177,503],[683,500]]},{"text":"日我们伟大领袖毛主席和他的亲密战友、我们的付统师林付主席接见了全体代表，这是非常","box":[[27,497],[535,501],[535,518],[27,513]]},{"text":"急，郑州铁路局的北站没有摘好，南站问志很着急·所以交通运有一点通不过，就会影聘","box":[[682,505],[1178,508],[1178,521],[682,518]]},{"text":"光荣的，非常幸福的一件大事。（众高呼：毛主席万岁！毛主席万万岁1）我们看了你们开","box":[[31,518],[535,522],[535,535],[31,531]]},{"text":"全局·再看看西北：本来西安局工作不错现在西安局还没有正式或立革命委员会，西安局的","box":[[683,524],[1177,526],[1177,540],[683,538]]},{"text":"会的简报，这两个月得到很大收获。简单地说，会议期间你们经过学习了毛主席一系列的最","box":[[32,537],[535,540],[535,554],[32,550]]},{"text":"美键在洛阳，宝成线那里通不过，积压车辆比较多。成都局也积压车，呼和浩特有时爱车发不","box":[[683,544],[1177,546],[1177,558],[683,555]]},{"text":"新指示，学习了林付主席三月二十四日重要指示，学习了中央、中央文革几位责负同志的讲","box":[[29,554],[535,559],[535,575],[29,570]]},{"text":"出米。所以西安局是西北、西南的关键，西安局工作没有做好。成都局开始准条或立革命委","box":[[683,562],[1178,563],[1178,577],[683,575]]},{"text":"话，还有去年江青同志“九·五”讲话。学习后，大家提高了思想水平、认识水平，对于促进","box":[[29,575],[534,579],[534,592],[29,588]]},{"text":"员会，因为成市成立了革命委员会，推动了成都局革命委员会的成立。但治阳道不过，国","box":[[683,581],[1179,583],[1179,596],[683,595]]},{"text":"你们法路、交通系统的无产阶级革合派大联合和革命三结合起了很大作用。在这两个月内","box":[[30,595],[524,599],[524,610],[29,606]]},{"text":"安局这条线上保密车有国干柄，占三分之一·这说明，有几个点通不过，就影响藻个运幢。","box":[[681,600],[1174,601],[1174,615],[681,614]]},{"text":"便你们过去没有达成协议的达成了，过去已经大联合的，这次实现了革命三结合，有的成立","box":[[26,613],[533,616],[533,630],[26,627]]},{"text":"从全局看，形势大好，应该越来越好，但几个点打不通，就阻得前进。比如，还有柳州也是","box":[[685,619],[1178,620],[1178,633],[685,632]]},{"text":"了革命委员会。截至五月十二日止，铁略和交通系统加在一起，参加会议的共一千五百八十","box":[[27,632],[532,636],[532,649],[27,646]]},{"text":"一个关键施方，它还接南、广西，文连接润桂线、湛江海运。从重庆、成都、昆明来的，","box":[[688,640],[1177,640],[1177,651],[688,651]]},{"text":"九个单位，已实现革命委员会或达成革命三结合协议的估百分之八十五，实现革命大联合的","box":[[25,652],[532,654],[532,668],[25,665]]},{"text":"从機州出口。这一条线有一个点通不过，不但柳州本身，还加上贵州的麻尾、部匀，这几个","box":[[684,657],[1180,657],[1180,670],[684,671]]},{"text":"占百分之十二。加在一起共百分之九十七：只有百分之三还没有达成革命大联合协议，这个","box":[[24,670],[531,673],[531,688],[24,685]]},{"text":"点道不过，影响了我们支援越南，支援世界革命。我们续路、交酒两个系统晶负有授外任","box":[[685,677],[1182,675],[1182,689],[685,690]]},{"text":"比例很小。你们的收获很大，应该庆贺你们，这次努力学习取得这样大的成绩。（众高呼","box":[[23,690],[524,693],[524,706],[23,704]]},{"text":"务，棵州局迪不过，影响就很大。尽答东面这条线很好，从北京到天津，津一直到沪","box":[[682,696],[1182,694],[1182,708],[682,710]]},{"text":"毛主席万岁！万万岁！）这样的成绩，不论铁路、交通系统，港口，对运有所促进，三月份","box":[[23,709],[530,713],[530,726],[23,722]]},{"text":"杭、渐都很好，但它不如内地几条线重要。从这几个例子可以看出，为什是铁路，交部","box":[[684,716],[1182,714],[1182,726],[684,727]]},{"text":"比二月份好，四月份比三月份好，比重增长，三月份增长快一点。成绩应当背定。绝大多数","box":[[23,728],[531,732],[531,747],[23,742]]},{"text":"门一道开这个会呢？而且开得这您长，就是要使大家有个全局起念。过去分开开会，但头全","box":[[683,734],[1182,732],[1182,746],[683,748]]},{"text":"单位是努力要把抓革命、促生产、促工作、促备搞好，因为真正的联合起来，实现三结合，","box":[[22,746],[523,752],[523,766],[21,760]]},{"text":"局考虑，还是合起来开。经过中央文革回志虑，分开开会，不容易有全局念，也不好解","box":[[685,754],[1184,751],[1184,765],[685,767]]},{"text":"成立了革命委员会。高举毛泽东思想伟大红旗，站在毛主席的革命路线上，按照毛主席指示","box":[[22,766],[531,771],[531,784],[21,779]]},{"text":"办事。从单位上看，不论是铁略局、铁路分局、名站、段，铁路工厂，都是如此。从港务局","box":[[19,783],[532,789],[532,805],[19,799]]},{"text":"决问题，所以合息来开。这次把金同十八个铁路局，五十二个分局，还有等于分局十个共","box":[[684,774],[1185,771],[1185,783],[684,787]]},{"text":"八十个单位，加上站、段，还有工厂，铁器票统共一千三百多个单位交通系统也如此，不","box":[[684,793],[1187,789],[1187,803],[684,807]]},{"text":"2","box":[[46,814],[80,814],[80,825],[46,825]]}],"dimensions":{"height":900,"width":1200}}